py3o.renderers.juno-0.8.1-py2.7-nspkg.pth
py3o.renderers.juno-0.8.1.dist-info/DESCRIPTION.rst
py3o.renderers.juno-0.8.1.dist-info/top_level.txt
py3o.renderers.juno-0.8.1.dist-info/zip-safe
py3o.renderers.juno-0.8.1.dist-info/METADATA
py3o.renderers.juno-0.8.1.dist-info/RECORD
py3o.renderers.juno-0.8.1.dist-info/WHEEL
py3o.renderers.juno-0.8.1.dist-info/metadata.json
py3o.renderers.juno-0.8.1.dist-info/namespace_packages.txt
py3o/renderers/__init__.py
py3o/renderers/juno/main.py
py3o/renderers/juno/__init__.py
py3o/renderers/juno/py3oconverter.jar
