Metadata-Version: 2.0
Name: py3o.renderers.juno
Version: 0.8.1
Summary: A Java based driver for py3o
Home-page: http://bitbucket.org/faide/py3o.renderers.juno
Author: Florent Aide & Jerome Collette
Author-email: florent.aide@gmail.com, collette.jerome@gmail.com
License: BSD License
Keywords: LibreOffice OpenOffice PDF
Platform: UNKNOWN
Classifier: Programming Language :: Python
Classifier: Topic :: Software Development :: Libraries :: Python Modules
Classifier: Development Status :: 4 - Beta
Classifier: Intended Audience :: Developers
Classifier: License :: OSI Approved :: BSD License
Classifier: Operating System :: OS Independent
Classifier: Programming Language :: Java
Classifier: Programming Language :: Python :: 2
Classifier: Topic :: Printing
Requires-Dist: setuptools
Requires-Dist: jpype1
